medium_scraper/__init__.py
medium_scraper/concurrent.py
medium_scraper/models.py
medium_scraper/progress.py
medium_scraper/explorer/__init__.py
medium_scraper/explorer/medium_explorer.py
medium_scraper/parser/__init__.py
medium_scraper/parser/medium_parser.py
medium_scraper/request_sender/__init__.py
medium_scraper/request_sender/base.py
medium_scraper/request_sender/cache_backend.py
medium_scraper/request_sender/cached_sender.py
medium_scraper/request_sender/decodo_scraper_sender.py
medium_scraper/request_sender/requests_sender.py
medium_scraper-0.1.1.dist-info/LICENSE
medium_scraper-0.1.1.dist-info/METADATA
medium_scraper-0.1.1.dist-info/WHEEL
medium_scraper-0.1.1.dist-info/top_level.txt
medium_scraper-0.1.1.dist-info/RECORD
