Metadata-Version: 2.1
Name: medium-scraper
Version: 0.1.1
Summary: High-scale Medium scraper: request abstraction and HTML->Markdown parser
Author: Sarper AVCI
Requires-Python: >=3.8
License-File: LICENSE
Requires-Dist: curl-cffi
Requires-Dist: beautifulsoup4>=4.12.0
Requires-Dist: markdownify>=0.13.0
